eventline/__init__.py
eventline/account.py
eventline/api_client.py
eventline/api_object.py
eventline/client.py
eventline/command_execution.py
eventline/context.py
eventline/environment.py
eventline/event.py
eventline/organization.py
eventline/pagination.py
eventline/pipeline.py
eventline/project.py
eventline/resource.py
eventline/task.py
eventline/data/cacert.pem
examples/create_custom_event.py
examples/create_project.py
examples/current_account.py
examples/execute_command.py
examples/fetch_resource_spec.py
examples/list_accounts.py
examples/list_command_executions.py
tests/__init__.py
tests/client_test.py
eventline-0.2.5.dist-info/LICENSE
eventline-0.2.5.dist-info/METADATA
eventline-0.2.5.dist-info/WHEEL
eventline-0.2.5.dist-info/top_level.txt
eventline-0.2.5.dist-info/RECORD
