Metadata-Version: 2.1
Name: eventline
Version: 0.2.5
Summary: Tools to interact with the Eventline platform
Home-page: https://github.com/exograd/py-eventline
Author: Exograd
Author-email: contact@exograd.com
Project-URL: Bug Tracker, https://github.com/exograd/py-eventline/issues
Classifier: Programming Language :: Python :: 3
Classifier: License :: OSI Approved :: ISC License (ISCL)
Classifier: Operating System :: OS Independent
Requires-Python: >=3.7
License-File: LICENSE
Requires-Dist: pyOpenSSL
Requires-Dist: python-dateutil
Requires-Dist: urllib3
Provides-Extra: checks
Requires-Dist: types-pyOpenSSL ; extra == 'checks'
Requires-Dist: types-python-dateutil ; extra == 'checks'
Requires-Dist: types-urllib3 ; extra == 'checks'
